[
  {
    "matchup": "Atalanta – Inter",
    "event_url": "https://livetv.sx/enx/eventinfo/326707876__/",
    "event_id": "326707876",
    "date_time": "28 December at 20:45",
    "competition": "Italy. Serie A",
    "parsed_datetime": "2025-12-28T20:45:00",
    "logo_alt": "Italy. Serie A",
    "is_live": true,
    "team_logos": [
      {
        "team_name": "Atalanta",
        "logo_url": "https://cdn.livetv872.me/img/teams/fullsize/ods/59.gif"
      },
      {
        "team_name": "Inter",
        "logo_url": "https://cdn.livetv872.me/img/teams/fullsize/ods/26888.gif"
      }
    ],
    "streams": [
      {
        "language": "English",
        "flag_src": "https://cdn.livetv872.me/img/linkflag/2.png",
        "bitrate": "Bit Rate (Kbps)",
        "stream_url": "https://cdn.livetv872.me/webplayer2.php?t=alieztv&c=242313&lang=en&eid=326707876&lid=2819130&ci=11&si=1",
        "stream_title": "",
        "stream_type": ""
      },
      {
        "language": "English",
        "flag_src": "https://cdn.livetv872.me/img/linkflag/2.png",
        "bitrate": "Bit Rate (Kbps)",
        "stream_url": "https://cdn.livetv872.me/webplayer2.php?t=alieztv&c=242325&lang=en&eid=326707876&lid=2812095&ci=11&si=1",
        "stream_title": "",
        "stream_type": ""
      },
      {
        "language": "English",
        "flag_src": "https://cdn.livetv872.me/img/linkflag/2.png",
        "bitrate": "Bit Rate (Kbps)",
        "stream_url": "https://cdn.livetv872.me/webplayer2.php?t=alieztv&c=243366&lang=en&eid=326707876&lid=2915274&ci=11&si=1",
        "stream_title": "",
        "stream_type": ""
      },
      {
        "language": "English",
        "flag_src": "https://cdn.livetv872.me/img/linkflag/2.png",
        "bitrate": "Bit Rate (Kbps)",
        "stream_url": "https://cdn.livetv872.me/webplayer2.php?t=alieztv&c=244432&lang=en&eid=326707876&lid=2914741&ci=11&si=1",
        "stream_title": "",
        "stream_type": ""
      },
      {
        "language": "English",
        "flag_src": "https://cdn.livetv872.me/img/linkflag/2.png",
        "bitrate": "Bit Rate (Kbps)",
        "stream_url": "https://cdn.livetv872.me/webplayer.php?t=ifr&c=2661149&lang=en&eid=326707876&lid=2661149&ci=11&si=1",
        "stream_title": "пїЅпїЅпїЅпїЅпїЅпїЅпїЅ пїЅ пїЅпїЅпїЅпїЅпїЅ пїЅпїЅпїЅпїЅ",
        "stream_type": "Web"
      },
      {
        "language": "English",
        "flag_src": "https://cdn.livetv872.me/img/linkflag/2.png",
        "bitrate": "Bit Rate (Kbps)",
        "stream_url": "https://cdn.livetv872.me/webplayer.php?t=ifr&c=2915155&lang=en&eid=326707876&lid=2915155&ci=11&si=1",
        "stream_title": "пїЅпїЅпїЅпїЅпїЅпїЅпїЅ пїЅ пїЅпїЅпїЅпїЅпїЅ пїЅпїЅпїЅпїЅ",
        "stream_type": "Web"
      },
      {
        "language": "English",
        "flag_src": "https://cdn.livetv872.me/img/linkflag/2.png",
        "bitrate": "Bit Rate (Kbps)",
        "stream_url": "https://cdn.livetv872.me/webplayer.php?t=ifr&c=2869946&lang=en&eid=326707876&lid=2869946&ci=11&si=1",
        "stream_title": "пїЅпїЅпїЅпїЅпїЅпїЅпїЅ пїЅ пїЅпїЅпїЅпїЅпїЅ пїЅпїЅпїЅпїЅ",
        "stream_type": "Web"
      },
      {
        "language": "English",
        "flag_src": "https://cdn.livetv872.me/img/linkflag/2.png",
        "bitrate": "Bit Rate (Kbps)",
        "stream_url": "https://cdn.livetv872.me/webplayer.php?t=ifr&c=2915111&lang=en&eid=326707876&lid=2915111&ci=11&si=1",
        "stream_title": "пїЅпїЅпїЅпїЅпїЅпїЅпїЅ пїЅ пїЅпїЅпїЅпїЅпїЅ пїЅпїЅпїЅпїЅ",
        "stream_type": "Web"
      }
    ]
  },
  {
    "matchup": "Sporting – Rio Ave",
    "event_url": "https://livetv.sx/enx/eventinfo/326716564__/",
    "event_id": "326716564",
    "date_time": "28 December at 21:30",
    "competition": "Portugal. Primeira Liga",
    "parsed_datetime": "2025-12-28T21:30:00",
    "logo_alt": "Portugal. Primeira Liga",
    "is_live": true,
    "team_logos": [
      {
        "team_name": "Sporting",
        "logo_url": "https://cdn.livetv872.me/img/teams/fullsize/ods/340.gif"
      },
      {
        "team_name": "Rio Ave",
        "logo_url": "https://cdn.livetv872.me/img/teams/fullsize/ods/1120.gif"
      }
    ],
    "streams": [
      {
        "language": "English",
        "flag_src": "https://cdn.livetv872.me/img/linkflag/2.png",
        "bitrate": "Bit Rate (Kbps)",
        "stream_url": "https://cdn.livetv872.me/webplayer2.php?t=alieztv&c=241816&lang=en&eid=326716564&lid=2822880&ci=28&si=1",
        "stream_title": "",
        "stream_type": ""
      },
      {
        "language": "English",
        "flag_src": "https://cdn.livetv872.me/img/linkflag/2.png",
        "bitrate": "Bit Rate (Kbps)",
        "stream_url": "https://cdn.livetv872.me/webplayer2.php?t=alieztv&c=243368&lang=en&eid=326716564&lid=2915275&ci=28&si=1",
        "stream_title": "",
        "stream_type": ""
      },
      {
        "language": "Serbian",
        "flag_src": "https://cdn.livetv872.me/img/linkflag/17.png",
        "bitrate": "Bit Rate (Kbps)",
        "stream_url": "https://cdn.livetv872.me/webplayer2.php?t=alieztv&c=245324&lang=en&eid=326716564&lid=2912118&ci=28&si=1",
        "stream_title": "",
        "stream_type": ""
      },
      {
        "language": "Portuguese",
        "flag_src": "https://cdn.livetv872.me/img/linkflag/9.png",
        "bitrate": "Bit Rate (Kbps)",
        "stream_url": "https://cdn.livetv872.me/webplayer2.php?t=alieztv&c=245475&lang=en&eid=326716564&lid=2912763&ci=28&si=1",
        "stream_title": "",
        "stream_type": ""
      },
      {
        "language": "German",
        "flag_src": "https://cdn.livetv872.me/img/linkflag/13.png",
        "bitrate": "Bit Rate (Kbps)",
        "stream_url": "https://cdn.livetv872.me/webplayer2.php?t=alieztv&c=245484&lang=en&eid=326716564&lid=2915830&ci=28&si=1",
        "stream_title": "",
        "stream_type": ""
      },
      {
        "language": "Russian",
        "flag_src": "https://cdn.livetv872.me/img/linkflag/1.png",
        "bitrate": "Bit Rate (Kbps)",
        "stream_url": "https://cdn.livetv872.me/webplayer2.php?t=alieztv&c=241480&lang=en&eid=326716564&lid=2914928&ci=28&si=1",
        "stream_title": "",
        "stream_type": ""
      },
      {
        "language": "Russian",
        "flag_src": "https://cdn.livetv872.me/img/linkflag/1.png",
        "bitrate": "Bit Rate (Kbps)",
        "stream_url": "https://cdn.livetv872.me/webplayer2.php?t=alieztv&c=241815&lang=en&eid=326716564&lid=2914929&ci=28&si=1",
        "stream_title": "",
        "stream_type": ""
      },
      {
        "language": "",
        "flag_src": "https://cdn.livetv872.me/img/linkflag/0.png",
        "bitrate": "Bit Rate (Kbps)",
        "stream_url": "https://cdn.livetv872.me/webplayer2.php?t=alieztv&c=241990&lang=en&eid=326716564&lid=2915857&ci=28&si=1",
        "stream_title": "",
        "stream_type": ""
      }
    ]
  },
  {
    "matchup": "Ivory Coast CIV – Cameroon CMR",
    "event_url": "https://livetv.sx/enx/eventinfo/326708087__/",
    "event_id": "326708087",
    "date_time": "28 December at 21:00",
    "competition": "Africa Cup of Nations",
    "parsed_datetime": "2025-12-28T21:00:00",
    "logo_alt": "Africa Cup of Nations",
    "is_live": true,
    "team_logos": [
      {
        "team_name": "Ivory Coast CIV",
        "logo_url": "https://cdn.livetv872.me/img/teams/fullsize/ods/flag225.gif"
      },
      {
        "team_name": "Cameroon CMR",
        "logo_url": "https://cdn.livetv872.me/img/teams/fullsize/ods/flag38.gif"
      }
    ],
    "streams": [
      {
        "language": "English",
        "flag_src": "https://cdn.livetv872.me/img/linkflag/2.png",
        "bitrate": "Bit Rate (Kbps)",
        "stream_url": "https://cdn.livetv872.me/webplayer2.php?t=alieztv&c=245732&lang=en&eid=326708087&lid=2914301&ci=311&si=1",
        "stream_title": "",
        "stream_type": ""
      },
      {
        "language": "English",
        "flag_src": "https://cdn.livetv872.me/img/linkflag/2.png",
        "bitrate": "Bit Rate (Kbps)",
        "stream_url": "https://cdn.livetv872.me/webplayer2.php?t=alieztv&c=242328&lang=en&eid=326708087&lid=2914163&ci=311&si=1",
        "stream_title": "",
        "stream_type": ""
      },
      {
        "language": "English",
        "flag_src": "https://cdn.livetv872.me/img/linkflag/2.png",
        "bitrate": "Bit Rate (Kbps)",
        "stream_url": "https://cdn.livetv872.me/webplayer.php?t=ifr&c=2666840&lang=en&eid=326708087&lid=2666840&ci=311&si=1",
        "stream_title": "пїЅпїЅпїЅпїЅпїЅпїЅпїЅ пїЅ пїЅпїЅпїЅпїЅпїЅ пїЅпїЅпїЅпїЅ",
        "stream_type": "Web"
      },
      {
        "language": "English",
        "flag_src": "https://cdn.livetv872.me/img/linkflag/2.png",
        "bitrate": "Bit Rate (Kbps)",
        "stream_url": "https://cdn.livetv872.me/webplayer.php?t=ifr&c=2914821&lang=en&eid=326708087&lid=2914821&ci=311&si=1",
        "stream_title": "пїЅпїЅпїЅпїЅпїЅпїЅпїЅ пїЅ пїЅпїЅпїЅпїЅпїЅ пїЅпїЅпїЅпїЅ",
        "stream_type": "Web"
      },
      {
        "language": "English",
        "flag_src": "https://cdn.livetv872.me/img/linkflag/2.png",
        "bitrate": "Bit Rate (Kbps)",
        "stream_url": "https://cdn.livetv872.me/webplayer.php?t=ifr&c=2915093&lang=en&eid=326708087&lid=2915093&ci=311&si=1",
        "stream_title": "пїЅпїЅпїЅпїЅпїЅпїЅпїЅ пїЅ пїЅпїЅпїЅпїЅпїЅ пїЅпїЅпїЅпїЅ",
        "stream_type": "Web"
      },
      {
        "language": "English",
        "flag_src": "https://cdn.livetv872.me/img/linkflag/2.png",
        "bitrate": "Bit Rate (Kbps)",
        "stream_url": "https://cdn.livetv872.me/webplayer.php?t=ifr&c=2914819&lang=en&eid=326708087&lid=2914819&ci=311&si=1",
        "stream_title": "пїЅпїЅпїЅпїЅпїЅпїЅпїЅ пїЅ пїЅпїЅпїЅпїЅпїЅ пїЅпїЅпїЅпїЅ",
        "stream_type": "Web"
      },
      {
        "language": "English",
        "flag_src": "https://cdn.livetv872.me/img/linkflag/2.png",
        "bitrate": "Bit Rate (Kbps)",
        "stream_url": "https://cdn.livetv872.me/webplayer.php?t=ifr&c=2915402&lang=en&eid=326708087&lid=2915402&ci=311&si=1",
        "stream_title": "пїЅпїЅпїЅпїЅпїЅпїЅпїЅ пїЅ пїЅпїЅпїЅпїЅпїЅ пїЅпїЅпїЅпїЅ",
        "stream_type": "Web"
      },
      {
        "language": "English",
        "flag_src": "https://cdn.livetv872.me/img/linkflag/2.png",
        "bitrate": "Bit Rate (Kbps)",
        "stream_url": "https://cdn.livetv872.me/webplayer.php?t=ifr&c=2914564&lang=en&eid=326708087&lid=2914564&ci=311&si=1",
        "stream_title": "пїЅпїЅпїЅпїЅпїЅпїЅпїЅ пїЅ пїЅпїЅпїЅпїЅпїЅ пїЅпїЅпїЅпїЅ",
        "stream_type": "Web"
      }
    ]
  },
  {
    "matchup": "Ivory Coast CIV – Cameroon CMR",
    "event_url": "https://livetv.sx/enx/eventinfo/326708087__/",
    "event_id": "326708087",
    "date_time": "28 December at 21:00",
    "competition": "Africa Cup of Nations",
    "parsed_datetime": "2025-12-28T21:00:00",
    "logo_alt": "Africa Cup of Nations",
    "is_live": true,
    "team_logos": [
      {
        "team_name": "Ivory Coast CIV",
        "logo_url": "https://cdn.livetv872.me/img/teams/fullsize/ods/flag225.gif"
      },
      {
        "team_name": "Cameroon CMR",
        "logo_url": "https://cdn.livetv872.me/img/teams/fullsize/ods/flag38.gif"
      }
    ],
    "streams": [
      {
        "language": "English",
        "flag_src": "https://cdn.livetv872.me/img/linkflag/2.png",
        "bitrate": "Bit Rate (Kbps)",
        "stream_url": "https://cdn.livetv872.me/webplayer2.php?t=alieztv&c=245732&lang=en&eid=326708087&lid=2914301&ci=311&si=1",
        "stream_title": "",
        "stream_type": ""
      },
      {
        "language": "English",
        "flag_src": "https://cdn.livetv872.me/img/linkflag/2.png",
        "bitrate": "Bit Rate (Kbps)",
        "stream_url": "https://cdn.livetv872.me/webplayer2.php?t=alieztv&c=242328&lang=en&eid=326708087&lid=2914163&ci=311&si=1",
        "stream_title": "",
        "stream_type": ""
      },
      {
        "language": "English",
        "flag_src": "https://cdn.livetv872.me/img/linkflag/2.png",
        "bitrate": "Bit Rate (Kbps)",
        "stream_url": "https://cdn.livetv872.me/webplayer.php?t=ifr&c=2666840&lang=en&eid=326708087&lid=2666840&ci=311&si=1",
        "stream_title": "пїЅпїЅпїЅпїЅпїЅпїЅпїЅ пїЅ пїЅпїЅпїЅпїЅпїЅ пїЅпїЅпїЅпїЅ",
        "stream_type": "Web"
      },
      {
        "language": "English",
        "flag_src": "https://cdn.livetv872.me/img/linkflag/2.png",
        "bitrate": "Bit Rate (Kbps)",
        "stream_url": "https://cdn.livetv872.me/webplayer.php?t=ifr&c=2914821&lang=en&eid=326708087&lid=2914821&ci=311&si=1",
        "stream_title": "пїЅпїЅпїЅпїЅпїЅпїЅпїЅ пїЅ пїЅпїЅпїЅпїЅпїЅ пїЅпїЅпїЅпїЅ",
        "stream_type": "Web"
      },
      {
        "language": "English",
        "flag_src": "https://cdn.livetv872.me/img/linkflag/2.png",
        "bitrate": "Bit Rate (Kbps)",
        "stream_url": "https://cdn.livetv872.me/webplayer.php?t=ifr&c=2915093&lang=en&eid=326708087&lid=2915093&ci=311&si=1",
        "stream_title": "пїЅпїЅпїЅпїЅпїЅпїЅпїЅ пїЅ пїЅпїЅпїЅпїЅпїЅ пїЅпїЅпїЅпїЅ",
        "stream_type": "Web"
      },
      {
        "language": "English",
        "flag_src": "https://cdn.livetv872.me/img/linkflag/2.png",
        "bitrate": "Bit Rate (Kbps)",
        "stream_url": "https://cdn.livetv872.me/webplayer.php?t=ifr&c=2914819&lang=en&eid=326708087&lid=2914819&ci=311&si=1",
        "stream_title": "пїЅпїЅпїЅпїЅпїЅпїЅпїЅ пїЅ пїЅпїЅпїЅпїЅпїЅ пїЅпїЅпїЅпїЅ",
        "stream_type": "Web"
      },
      {
        "language": "English",
        "flag_src": "https://cdn.livetv872.me/img/linkflag/2.png",
        "bitrate": "Bit Rate (Kbps)",
        "stream_url": "https://cdn.livetv872.me/webplayer.php?t=ifr&c=2915402&lang=en&eid=326708087&lid=2915402&ci=311&si=1",
        "stream_title": "пїЅпїЅпїЅпїЅпїЅпїЅпїЅ пїЅ пїЅпїЅпїЅпїЅпїЅ пїЅпїЅпїЅпїЅ",
        "stream_type": "Web"
      },
      {
        "language": "English",
        "flag_src": "https://cdn.livetv872.me/img/linkflag/2.png",
        "bitrate": "Bit Rate (Kbps)",
        "stream_url": "https://cdn.livetv872.me/webplayer.php?t=ifr&c=2914564&lang=en&eid=326708087&lid=2914564&ci=311&si=1",
        "stream_title": "пїЅпїЅпїЅпїЅпїЅпїЅпїЅ пїЅ пїЅпїЅпїЅпїЅпїЅ пїЅпїЅпїЅпїЅ",
        "stream_type": "Web"
      }
    ]
  },
  {
    "matchup": "Sporting – Rio Ave",
    "event_url": "https://livetv.sx/enx/eventinfo/326716564__/",
    "event_id": "326716564",
    "date_time": "28 December at 21:30",
    "competition": "Portugal. Primeira Liga",
    "parsed_datetime": "2025-12-28T21:30:00",
    "logo_alt": "Portugal. Primeira Liga",
    "is_live": true,
    "team_logos": [
      {
        "team_name": "Sporting",
        "logo_url": "https://cdn.livetv872.me/img/teams/fullsize/ods/340.gif"
      },
      {
        "team_name": "Rio Ave",
        "logo_url": "https://cdn.livetv872.me/img/teams/fullsize/ods/1120.gif"
      }
    ],
    "streams": [
      {
        "language": "English",
        "flag_src": "https://cdn.livetv872.me/img/linkflag/2.png",
        "bitrate": "Bit Rate (Kbps)",
        "stream_url": "https://cdn.livetv872.me/webplayer2.php?t=alieztv&c=241816&lang=en&eid=326716564&lid=2822880&ci=28&si=1",
        "stream_title": "",
        "stream_type": ""
      },
      {
        "language": "English",
        "flag_src": "https://cdn.livetv872.me/img/linkflag/2.png",
        "bitrate": "Bit Rate (Kbps)",
        "stream_url": "https://cdn.livetv872.me/webplayer2.php?t=alieztv&c=243368&lang=en&eid=326716564&lid=2915275&ci=28&si=1",
        "stream_title": "",
        "stream_type": ""
      },
      {
        "language": "Serbian",
        "flag_src": "https://cdn.livetv872.me/img/linkflag/17.png",
        "bitrate": "Bit Rate (Kbps)",
        "stream_url": "https://cdn.livetv872.me/webplayer2.php?t=alieztv&c=245324&lang=en&eid=326716564&lid=2912118&ci=28&si=1",
        "stream_title": "",
        "stream_type": ""
      },
      {
        "language": "Portuguese",
        "flag_src": "https://cdn.livetv872.me/img/linkflag/9.png",
        "bitrate": "Bit Rate (Kbps)",
        "stream_url": "https://cdn.livetv872.me/webplayer2.php?t=alieztv&c=245475&lang=en&eid=326716564&lid=2912763&ci=28&si=1",
        "stream_title": "",
        "stream_type": ""
      },
      {
        "language": "German",
        "flag_src": "https://cdn.livetv872.me/img/linkflag/13.png",
        "bitrate": "Bit Rate (Kbps)",
        "stream_url": "https://cdn.livetv872.me/webplayer2.php?t=alieztv&c=245484&lang=en&eid=326716564&lid=2915830&ci=28&si=1",
        "stream_title": "",
        "stream_type": ""
      },
      {
        "language": "Russian",
        "flag_src": "https://cdn.livetv872.me/img/linkflag/1.png",
        "bitrate": "Bit Rate (Kbps)",
        "stream_url": "https://cdn.livetv872.me/webplayer2.php?t=alieztv&c=241480&lang=en&eid=326716564&lid=2914928&ci=28&si=1",
        "stream_title": "",
        "stream_type": ""
      },
      {
        "language": "Russian",
        "flag_src": "https://cdn.livetv872.me/img/linkflag/1.png",
        "bitrate": "Bit Rate (Kbps)",
        "stream_url": "https://cdn.livetv872.me/webplayer2.php?t=alieztv&c=241815&lang=en&eid=326716564&lid=2914929&ci=28&si=1",
        "stream_title": "",
        "stream_type": ""
      },
      {
        "language": "",
        "flag_src": "https://cdn.livetv872.me/img/linkflag/0.png",
        "bitrate": "Bit Rate (Kbps)",
        "stream_url": "https://cdn.livetv872.me/webplayer2.php?t=alieztv&c=241990&lang=en&eid=326716564&lid=2915857&ci=28&si=1",
        "stream_title": "",
        "stream_type": ""
      }
    ]
  },
  {
    "matchup": "Atalanta – Inter",
    "event_url": "https://livetv.sx/enx/eventinfo/326707876__/",
    "event_id": "326707876",
    "date_time": "28 December at 20:45",
    "competition": "Italy. Serie A",
    "parsed_datetime": "2025-12-28T20:45:00",
    "logo_alt": "Italy. Serie A",
    "is_live": true,
    "team_logos": [
      {
        "team_name": "Atalanta",
        "logo_url": "https://cdn.livetv872.me/img/teams/fullsize/ods/59.gif"
      },
      {
        "team_name": "Inter",
        "logo_url": "https://cdn.livetv872.me/img/teams/fullsize/ods/26888.gif"
      }
    ],
    "streams": [
      {
        "language": "English",
        "flag_src": "https://cdn.livetv872.me/img/linkflag/2.png",
        "bitrate": "Bit Rate (Kbps)",
        "stream_url": "https://cdn.livetv872.me/webplayer2.php?t=alieztv&c=242313&lang=en&eid=326707876&lid=2819130&ci=11&si=1",
        "stream_title": "",
        "stream_type": ""
      },
      {
        "language": "English",
        "flag_src": "https://cdn.livetv872.me/img/linkflag/2.png",
        "bitrate": "Bit Rate (Kbps)",
        "stream_url": "https://cdn.livetv872.me/webplayer2.php?t=alieztv&c=242325&lang=en&eid=326707876&lid=2812095&ci=11&si=1",
        "stream_title": "",
        "stream_type": ""
      },
      {
        "language": "English",
        "flag_src": "https://cdn.livetv872.me/img/linkflag/2.png",
        "bitrate": "Bit Rate (Kbps)",
        "stream_url": "https://cdn.livetv872.me/webplayer2.php?t=alieztv&c=243366&lang=en&eid=326707876&lid=2915274&ci=11&si=1",
        "stream_title": "",
        "stream_type": ""
      },
      {
        "language": "English",
        "flag_src": "https://cdn.livetv872.me/img/linkflag/2.png",
        "bitrate": "Bit Rate (Kbps)",
        "stream_url": "https://cdn.livetv872.me/webplayer2.php?t=alieztv&c=244432&lang=en&eid=326707876&lid=2914741&ci=11&si=1",
        "stream_title": "",
        "stream_type": ""
      },
      {
        "language": "English",
        "flag_src": "https://cdn.livetv872.me/img/linkflag/2.png",
        "bitrate": "Bit Rate (Kbps)",
        "stream_url": "https://cdn.livetv872.me/webplayer.php?t=ifr&c=2661149&lang=en&eid=326707876&lid=2661149&ci=11&si=1",
        "stream_title": "пїЅпїЅпїЅпїЅпїЅпїЅпїЅ пїЅ пїЅпїЅпїЅпїЅпїЅ пїЅпїЅпїЅпїЅ",
        "stream_type": "Web"
      },
      {
        "language": "English",
        "flag_src": "https://cdn.livetv872.me/img/linkflag/2.png",
        "bitrate": "Bit Rate (Kbps)",
        "stream_url": "https://cdn.livetv872.me/webplayer.php?t=ifr&c=2915155&lang=en&eid=326707876&lid=2915155&ci=11&si=1",
        "stream_title": "пїЅпїЅпїЅпїЅпїЅпїЅпїЅ пїЅ пїЅпїЅпїЅпїЅпїЅ пїЅпїЅпїЅпїЅ",
        "stream_type": "Web"
      },
      {
        "language": "English",
        "flag_src": "https://cdn.livetv872.me/img/linkflag/2.png",
        "bitrate": "Bit Rate (Kbps)",
        "stream_url": "https://cdn.livetv872.me/webplayer.php?t=ifr&c=2869946&lang=en&eid=326707876&lid=2869946&ci=11&si=1",
        "stream_title": "пїЅпїЅпїЅпїЅпїЅпїЅпїЅ пїЅ пїЅпїЅпїЅпїЅпїЅ пїЅпїЅпїЅпїЅ",
        "stream_type": "Web"
      },
      {
        "language": "English",
        "flag_src": "https://cdn.livetv872.me/img/linkflag/2.png",
        "bitrate": "Bit Rate (Kbps)",
        "stream_url": "https://cdn.livetv872.me/webplayer.php?t=ifr&c=2915111&lang=en&eid=326707876&lid=2915111&ci=11&si=1",
        "stream_title": "пїЅпїЅпїЅпїЅпїЅпїЅпїЅ пїЅ пїЅпїЅпїЅпїЅпїЅ пїЅпїЅпїЅпїЅ",
        "stream_type": "Web"
      }
    ]
  }
]