[
  {
    "matchup": "Mozambique MOZ – Cameroon CMR",
    "event_url": "https://livetv.sx/enx/eventinfo/327305669__/",
    "event_id": "327305669",
    "date_time": "31 December at 20:00",
    "competition": "Africa Cup of Nations",
    "parsed_datetime": "2025-12-31T20:00:00",
    "logo_alt": "Africa Cup of Nations",
    "is_live": false,
    "team_logos": [
      {
        "team_name": "Mozambique MOZ",
        "logo_url": "https://cdn.livetv872.me/img/teams/fullsize/ods/flag135.gif"
      },
      {
        "team_name": "Cameroon CMR",
        "logo_url": "https://cdn.livetv872.me/img/teams/fullsize/ods/flag38.gif"
      }
    ],
    "streams": []
  },
  {
    "matchup": "Mozambique MOZ – Cameroon CMR",
    "event_url": "https://livetv.sx/enx/eventinfo/327305669__/",
    "event_id": "327305669",
    "date_time": "31 December at 20:00",
    "competition": "Africa Cup of Nations",
    "parsed_datetime": "2025-12-31T20:00:00",
    "logo_alt": "Africa Cup of Nations",
    "is_live": false,
    "team_logos": [
      {
        "team_name": "Mozambique MOZ",
        "logo_url": "https://cdn.livetv872.me/img/teams/fullsize/ods/flag135.gif"
      },
      {
        "team_name": "Cameroon CMR",
        "logo_url": "https://cdn.livetv872.me/img/teams/fullsize/ods/flag38.gif"
      }
    ],
    "streams": []
  },
  {
    "matchup": "Gabon GAB – Ivory Coast CIV",
    "event_url": "https://livetv.sx/enx/eventinfo/327305670__/",
    "event_id": "327305670",
    "date_time": "31 December at 20:00",
    "competition": "Africa Cup of Nations",
    "parsed_datetime": "2025-12-31T20:00:00",
    "logo_alt": "Africa Cup of Nations",
    "is_live": false,
    "team_logos": [
      {
        "team_name": "Gabon GAB",
        "logo_url": "https://cdn.livetv872.me/img/teams/fullsize/ods/flag69.gif"
      },
      {
        "team_name": "Ivory Coast CIV",
        "logo_url": "https://cdn.livetv872.me/img/teams/fullsize/ods/flag225.gif"
      }
    ],
    "streams": []
  },
  {
    "matchup": "Gabon GAB – Ivory Coast CIV",
    "event_url": "https://livetv.sx/enx/eventinfo/327305670__/",
    "event_id": "327305670",
    "date_time": "31 December at 20:00",
    "competition": "Africa Cup of Nations",
    "parsed_datetime": "2025-12-31T20:00:00",
    "logo_alt": "Africa Cup of Nations",
    "is_live": false,
    "team_logos": [
      {
        "team_name": "Gabon GAB",
        "logo_url": "https://cdn.livetv872.me/img/teams/fullsize/ods/flag69.gif"
      },
      {
        "team_name": "Ivory Coast CIV",
        "logo_url": "https://cdn.livetv872.me/img/teams/fullsize/ods/flag225.gif"
      }
    ],
    "streams": []
  }
]