[
  {
    "matchup": "Sturm Graz – Brugge",
    "event_url": "https://livetv.sx/enx/eventinfo/332185226__/",
    "event_id": "332185226",
    "date_time": "8 January at 15:00",
    "competition": "Friendly Match",
    "parsed_datetime": "2026-01-08T15:00:00",
    "logo_alt": "Friendly Match",
    "is_live": false,
    "team_logos": [
      {
        "team_name": "Sturm Graz",
        "logo_url": "https://cdn.livetv872.me/img/teams/fullsize/ods/4555.gif"
      },
      {
        "team_name": "Brugge",
        "logo_url": "https://cdn.livetv872.me/img/teams/fullsize/ods/4092.gif"
      }
    ],
    "streams": []
  },
  {
    "matchup": "Sturm Graz – Brugge",
    "event_url": "https://livetv.sx/enx/eventinfo/332185226__/",
    "event_id": "332185226",
    "date_time": "8 January at 15:00",
    "competition": "Friendly Match",
    "parsed_datetime": "2026-01-08T15:00:00",
    "logo_alt": "Friendly Match",
    "is_live": false,
    "team_logos": [
      {
        "team_name": "Sturm Graz",
        "logo_url": "https://cdn.livetv872.me/img/teams/fullsize/ods/4555.gif"
      },
      {
        "team_name": "Brugge",
        "logo_url": "https://cdn.livetv872.me/img/teams/fullsize/ods/4092.gif"
      }
    ],
    "streams": []
  },
  {
    "matchup": "Dibba Al-Fujairah – Khor Fakkan",
    "event_url": "https://livetv.sx/enx/eventinfo/328948757__/",
    "event_id": "328948757",
    "date_time": "8 January at 14:00",
    "competition": "UAE. Pro League",
    "parsed_datetime": "2026-01-08T14:00:00",
    "logo_alt": "UAE. Pro League",
    "is_live": false,
    "team_logos": [
      {
        "team_name": "Dibba Al-Fujairah",
        "logo_url": "https://cdn.livetv872.me/img/teams/fullsize/ods/35272.gif"
      },
      {
        "team_name": "Khor Fakkan",
        "logo_url": "https://cdn.livetv872.me/img/teams/fullsize/ods/9192.gif"
      }
    ],
    "streams": []
  },
  {
    "matchup": "Australia U-23 –  Thailand U-23",
    "event_url": "https://livetv.sx/enx/eventinfo/328938859__/",
    "event_id": "328938859",
    "date_time": "8 January at 12:30",
    "competition": "AFC U-23 Asian Cup",
    "parsed_datetime": "2026-01-08T12:30:00",
    "logo_alt": "AFC U-23 Asian Cup",
    "is_live": false,
    "team_logos": [
      {
        "team_name": "Australia U-23",
        "logo_url": "https://cdn.livetv872.me/img/teams/fullsize/ods/flag12.gif"
      },
      {
        "team_name": "Thailand U-23",
        "logo_url": "https://cdn.livetv872.me/img/teams/fullsize/ods/flag190.gif"
      }
    ],
    "streams": [
      {
        "language": "English",
        "flag_src": "https://cdn.livetv872.me/img/linkflag/2.png",
        "bitrate": "Bit Rate (Kbps)",
        "stream_url": "https://cdn.livetv872.me/webplayer.php?t=ifr&c=2920845&lang=en&eid=328938859&lid=2920845&ci=1019&si=1",
        "stream_title": "пїЅпїЅпїЅпїЅпїЅпїЅпїЅ пїЅ пїЅпїЅпїЅпїЅпїЅ пїЅпїЅпїЅпїЅ",
        "stream_type": "Web"
      },
      {
        "language": "",
        "flag_src": "https://cdn.livetv872.me/img/linkflag/0.png",
        "bitrate": "Bit Rate (Kbps)",
        "stream_url": "https://cdn.livetv872.me/webplayer2.php?t=youtube&c=4d1q6JO0whk&lang=en&eid=328938859&lid=2918265&ci=1019&si=1",
        "stream_title": "",
        "stream_type": ""
      },
      {
        "language": "Bulgarian",
        "flag_src": "https://cdn.livetv872.me/img/linkflag/16.png",
        "bitrate": "Bit Rate (Kbps)",
        "stream_url": "https://cdn.livetv872.me/webplayer.php?t=ifr&c=2666652&lang=en&eid=328938859&lid=2666652&ci=1019&si=1",
        "stream_title": "пїЅпїЅпїЅпїЅпїЅпїЅпїЅ пїЅ пїЅпїЅпїЅпїЅпїЅ пїЅпїЅпїЅпїЅ",
        "stream_type": "Web"
      },
      {
        "language": "",
        "flag_src": "https://cdn.livetv872.me/img/linkflag/0.png",
        "bitrate": "Bit Rate (Kbps)",
        "stream_url": "https://cdn.livetv872.me/webplayer.php?t=ifr&c=2923164&lang=en&eid=328938859&lid=2923164&ci=1019&si=1",
        "stream_title": "пїЅпїЅпїЅпїЅпїЅпїЅпїЅ пїЅ пїЅпїЅпїЅпїЅпїЅ пїЅпїЅпїЅпїЅ",
        "stream_type": "Voodc"
      },
      {
        "language": "",
        "flag_src": "https://cdn.livetv872.me/img/linkflag/0.png",
        "bitrate": "Bit Rate (Kbps)",
        "stream_url": "https://cdn.livetv872.me/webplayer.php?t=ifr&c=2923047&lang=en&eid=328938859&lid=2923047&ci=1019&si=1",
        "stream_title": "пїЅпїЅпїЅпїЅпїЅпїЅпїЅ пїЅ пїЅпїЅпїЅпїЅпїЅ пїЅпїЅпїЅпїЅ",
        "stream_type": "Web"
      },
      {
        "language": "",
        "flag_src": "https://cdn.livetv872.me/img/linkflag/0.png",
        "bitrate": "Bit Rate (Kbps)",
        "stream_url": "https://cdn.livetv872.me/webplayer.php?t=ifr&c=2922592&lang=en&eid=328938859&lid=2922592&ci=1019&si=1",
        "stream_title": "пїЅпїЅпїЅпїЅпїЅпїЅпїЅ пїЅ пїЅпїЅпїЅпїЅпїЅ пїЅпїЅпїЅпїЅ",
        "stream_type": "Web"
      }
    ]
  },
  {
    "matchup": "Al Hilal Omdurman – Etincelles",
    "event_url": "https://livetv.sx/enx/eventinfo/332185083__/",
    "event_id": "332185083",
    "date_time": "8 January at 14:00",
    "competition": "Rwanda. Premier League",
    "parsed_datetime": "2026-01-08T14:00:00",
    "logo_alt": "Rwanda. Premier League",
    "is_live": false,
    "team_logos": [
      {
        "team_name": "Al Hilal Omdurman",
        "logo_url": "https://cdn.livetv872.me/img/teams/fullsize/ods/11849.gif"
      },
      {
        "team_name": "Etincelles",
        "logo_url": "https://cdn.livetv872.me/img/teams/fullsize/ods/36540.gif"
      }
    ],
    "streams": []
  },
  {
    "matchup": "Lusitania – Leixoes",
    "event_url": "https://livetv.sx/enx/eventinfo/328998230__/",
    "event_id": "328998230",
    "date_time": "8 January at 21:15",
    "competition": "Portugal. Segunda Liga",
    "parsed_datetime": "2026-01-08T21:15:00",
    "logo_alt": "Portugal. Segunda Liga",
    "is_live": false,
    "team_logos": [
      {
        "team_name": "Lusitania",
        "logo_url": "https://cdn.livetv872.me/img/teams/fullsize/ods/11905.gif"
      },
      {
        "team_name": "Leixoes",
        "logo_url": "https://cdn.livetv872.me/img/teams/fullsize/ods/4380.gif"
      }
    ],
    "streams": []
  },
  {
    "matchup": "PSG – Marseille",
    "event_url": "https://livetv.sx/enx/eventinfo/328981389__/",
    "event_id": "328981389",
    "date_time": "8 January at 19:00",
    "competition": "France. Supercup",
    "parsed_datetime": "2026-01-08T19:00:00",
    "logo_alt": "France. Supercup",
    "is_live": false,
    "team_logos": [
      {
        "team_name": "PSG",
        "logo_url": "https://cdn.livetv872.me/img/teams/fullsize/ods/34520.gif"
      },
      {
        "team_name": "Marseille",
        "logo_url": "https://cdn.livetv872.me/img/teams/fullsize/ods/120.gif"
      }
    ],
    "streams": []
  },
  {
    "matchup": "Cascavel – Azuriz",
    "event_url": "https://livetv.sx/enx/eventinfo/329006828__/",
    "event_id": "329006828",
    "date_time": "8 January at 23:00",
    "competition": "Brazil. Campeonato Paranaense",
    "parsed_datetime": "2026-01-08T23:00:00",
    "logo_alt": "Brazil. Campeonato Paranaense",
    "is_live": false,
    "team_logos": [
      {
        "team_name": "Cascavel",
        "logo_url": "https://cdn.livetv872.me/img/teams/fullsize/ods/29904.gif"
      },
      {
        "team_name": "Azuriz",
        "logo_url": "https://cdn.livetv872.me/img/teams/fullsize/ods/29821.gif"
      }
    ],
    "streams": []
  },
  {
    "matchup": "Atletico Madrid – Real Madrid RM",
    "event_url": "https://livetv.sx/enx/eventinfo/328986655__/",
    "event_id": "328986655",
    "date_time": "8 January at 20:00",
    "competition": "Spain. Super Cup",
    "parsed_datetime": "2026-01-08T20:00:00",
    "logo_alt": "Spain. Super Cup",
    "is_live": false,
    "team_logos": [
      {
        "team_name": "Atletico Madrid",
        "logo_url": "https://cdn.livetv872.me/img/teams/fullsize/ods/35887.gif"
      },
      {
        "team_name": "Real Madrid RM",
        "logo_url": "https://cdn.livetv872.me/img/teams/fullsize/ods/33.gif"
      }
    ],
    "streams": []
  },
  {
    "matchup": "Preussen Muenster – Oud-Heverlee",
    "event_url": "https://livetv.sx/enx/eventinfo/332185368__/",
    "event_id": "332185368",
    "date_time": "8 January at 16:00",
    "competition": "Friendly Match",
    "parsed_datetime": "2026-01-08T16:00:00",
    "logo_alt": "Friendly Match",
    "is_live": false,
    "team_logos": [
      {
        "team_name": "Preussen Muenster",
        "logo_url": "https://cdn.livetv872.me/img/teams/fullsize/ods/16842.gif"
      },
      {
        "team_name": "Oud-Heverlee",
        "logo_url": "https://cdn.livetv872.me/img/teams/fullsize/ods/9067.gif"
      }
    ],
    "streams": []
  },
  {
    "matchup": "Milan – Genoa",
    "event_url": "https://livetv.sx/enx/eventinfo/328993655__/",
    "event_id": "328993655",
    "date_time": "8 January at 20:45",
    "competition": "Italy. Serie A",
    "parsed_datetime": "2026-01-08T20:45:00",
    "logo_alt": "Italy. Serie A",
    "is_live": false,
    "team_logos": [
      {
        "team_name": "Milan",
        "logo_url": "https://cdn.livetv872.me/img/teams/fullsize/ods/56.gif"
      },
      {
        "team_name": "Genoa",
        "logo_url": "https://cdn.livetv872.me/img/teams/fullsize/ods/71.gif"
      }
    ],
    "streams": []
  },
  {
    "matchup": "Arsenal – Liverpool",
    "event_url": "https://livetv.sx/enx/eventinfo/328993067__/",
    "event_id": "328993067",
    "date_time": "8 January at 21:00",
    "competition": "England. Premier League",
    "parsed_datetime": "2026-01-08T21:00:00",
    "logo_alt": "England. Premier League",
    "is_live": false,
    "team_logos": [
      {
        "team_name": "Arsenal",
        "logo_url": "https://cdn.livetv872.me/img/teams/fullsize/ods/142.gif"
      },
      {
        "team_name": "Liverpool",
        "logo_url": "https://cdn.livetv872.me/img/teams/fullsize/ods/30918.gif"
      }
    ],
    "streams": []
  },
  {
    "matchup": "Al-Qasim – Al-Shorta",
    "event_url": "https://livetv.sx/enx/eventinfo/331937280__/",
    "event_id": "331937280",
    "date_time": "8 January at 13:00",
    "competition": "Iraq. Premier League",
    "parsed_datetime": "2026-01-08T13:00:00",
    "logo_alt": "Iraq. Premier League",
    "is_live": false,
    "team_logos": [
      {
        "team_name": "Al-Qasim",
        "logo_url": "https://cdn.livetv872.me/img/teams/fullsize/ods/35660.gif"
      },
      {
        "team_name": "Al-Shorta",
        "logo_url": "https://cdn.livetv872.me/img/teams/fullsize/ods/8130.gif"
      }
    ],
    "streams": []
  },
  {
    "matchup": "Al Jazira – Ajman",
    "event_url": "https://livetv.sx/enx/eventinfo/328948758__/",
    "event_id": "328948758",
    "date_time": "8 January at 14:00",
    "competition": "UAE. Pro League",
    "parsed_datetime": "2026-01-08T14:00:00",
    "logo_alt": "UAE. Pro League",
    "is_live": false,
    "team_logos": [
      {
        "team_name": "Al Jazira",
        "logo_url": "https://cdn.livetv872.me/img/teams/fullsize/ods/9187.gif"
      },
      {
        "team_name": "Ajman",
        "logo_url": "https://cdn.livetv872.me/img/teams/fullsize/ods/7668.gif"
      }
    ],
    "streams": []
  },
  {
    "matchup": "Iraq U-23 –  China U-23",
    "event_url": "https://livetv.sx/enx/eventinfo/328953909__/",
    "event_id": "328953909",
    "date_time": "8 January at 15:00",
    "competition": "AFC U-23 Asian Cup",
    "parsed_datetime": "2026-01-08T15:00:00",
    "logo_alt": "AFC U-23 Asian Cup",
    "is_live": false,
    "team_logos": [
      {
        "team_name": "Iraq U-23",
        "logo_url": "https://cdn.livetv872.me/img/teams/fullsize/ods/flag96.gif"
      },
      {
        "team_name": "China U-23",
        "logo_url": "https://cdn.livetv872.me/img/teams/fullsize/ods/flag37.gif"
      }
    ],
    "streams": []
  },
  {
    "matchup": "Cremonese – Cagliari",
    "event_url": "https://livetv.sx/enx/eventinfo/328976400__/",
    "event_id": "328976400",
    "date_time": "8 January at 18:30",
    "competition": "Italy. Serie A",
    "parsed_datetime": "2026-01-08T18:30:00",
    "logo_alt": "Italy. Serie A",
    "is_live": false,
    "team_logos": [
      {
        "team_name": "Cremonese",
        "logo_url": "https://cdn.livetv872.me/img/teams/fullsize/ods/3913.gif"
      },
      {
        "team_name": "Cagliari",
        "logo_url": "https://cdn.livetv872.me/img/teams/fullsize/ods/62.gif"
      }
    ],
    "streams": []
  },
  {
    "matchup": "Al-Shahania – Al-Duhail",
    "event_url": "https://livetv.sx/enx/eventinfo/328956892__/",
    "event_id": "328956892",
    "date_time": "8 January at 15:30",
    "competition": "Qatar. Stars League",
    "parsed_datetime": "2026-01-08T15:30:00",
    "logo_alt": "Qatar. Stars League",
    "is_live": false,
    "team_logos": [
      {
        "team_name": "Al-Shahania",
        "logo_url": "https://cdn.livetv872.me/img/teams/fullsize/ods/6657.gif"
      },
      {
        "team_name": "Al-Duhail",
        "logo_url": "https://cdn.livetv872.me/img/teams/fullsize/ods/6326.gif"
      }
    ],
    "streams": []
  },
  {
    "matchup": "Al-Mosul – Erbil",
    "event_url": "https://livetv.sx/enx/eventinfo/331937281__/",
    "event_id": "331937281",
    "date_time": "8 January at 15:30",
    "competition": "Iraq. Premier League",
    "parsed_datetime": "2026-01-08T15:30:00",
    "logo_alt": "Iraq. Premier League",
    "is_live": false,
    "team_logos": [
      {
        "team_name": "Al-Mosul",
        "logo_url": "https://cdn.livetv872.me/img/teams/fullsize/ods/35661.gif"
      },
      {
        "team_name": "Erbil",
        "logo_url": "https://cdn.livetv872.me/img/teams/fullsize/ods/12074.gif"
      }
    ],
    "streams": []
  },
  {
    "matchup": "Preussen Muenster – Oud-Heverlee",
    "event_url": "https://livetv.sx/enx/eventinfo/332185368__/",
    "event_id": "332185368",
    "date_time": "8 January at 16:00",
    "competition": "Friendly Match",
    "parsed_datetime": "2026-01-08T16:00:00",
    "logo_alt": "Friendly Match",
    "is_live": false,
    "team_logos": [
      {
        "team_name": "Preussen Muenster",
        "logo_url": "https://cdn.livetv872.me/img/teams/fullsize/ods/16842.gif"
      },
      {
        "team_name": "Oud-Heverlee",
        "logo_url": "https://cdn.livetv872.me/img/teams/fullsize/ods/9067.gif"
      }
    ],
    "streams": []
  },
  {
    "matchup": "Al-Hilal Riyadh – Al-Hazem",
    "event_url": "https://livetv.sx/enx/eventinfo/328961182__/",
    "event_id": "328961182",
    "date_time": "8 January at 15:55",
    "competition": "Saudi Arabia. Pro League",
    "parsed_datetime": "2026-01-08T15:55:00",
    "logo_alt": "Saudi Arabia. Pro League",
    "is_live": false,
    "team_logos": [
      {
        "team_name": "Al-Hilal Riyadh",
        "logo_url": "https://cdn.livetv872.me/img/teams/fullsize/ods/26915.gif"
      },
      {
        "team_name": "Al-Hazem",
        "logo_url": "https://cdn.livetv872.me/img/teams/fullsize/ods/33055.gif"
      }
    ],
    "streams": []
  },
  {
    "matchup": "Ponte Preta do 20 – Esportiva Real U20",
    "event_url": "https://livetv.sx/enx/eventinfo/332235427_ponte_preta_do_20_esportiva_real_u20/",
    "event_id": "332235427",
    "date_time": "8 January at 17:00",
    "competition": "Brazil. Sao Paulo Youth Cup",
    "parsed_datetime": "2026-01-08T17:00:00",
    "logo_alt": "Brazil. Sao Paulo Youth Cup",
    "is_live": false,
    "team_logos": [],
    "streams": []
  },
  {
    "matchup": "Al Dhafra – Al Ain",
    "event_url": "https://livetv.sx/enx/eventinfo/328967373__/",
    "event_id": "328967373",
    "date_time": "8 January at 16:45",
    "competition": "UAE. Pro League",
    "parsed_datetime": "2026-01-08T16:45:00",
    "logo_alt": "UAE. Pro League",
    "is_live": false,
    "team_logos": [
      {
        "team_name": "Al Dhafra",
        "logo_url": "https://cdn.livetv872.me/img/teams/fullsize/ods/9186.gif"
      },
      {
        "team_name": "Al Ain",
        "logo_url": "https://cdn.livetv872.me/img/teams/fullsize/ods/1506.gif"
      }
    ],
    "streams": []
  },
  {
    "matchup": "Al-Shabab Manama – Al-Hidd",
    "event_url": "https://livetv.sx/enx/eventinfo/328965849__/",
    "event_id": "328965849",
    "date_time": "8 January at 17:00",
    "competition": "Bahrain. Premier League",
    "parsed_datetime": "2026-01-08T17:00:00",
    "logo_alt": "Bahrain. Premier League",
    "is_live": false,
    "team_logos": [
      {
        "team_name": "Al-Shabab Manama",
        "logo_url": "https://cdn.livetv872.me/img/teams/fullsize/ods/6691.gif"
      },
      {
        "team_name": "Al-Hidd",
        "logo_url": "https://cdn.livetv872.me/img/teams/fullsize/ods/6744.gif"
      }
    ],
    "streams": []
  },
  {
    "matchup": "Olympiakos Nicosia – Omonia Aradippou",
    "event_url": "https://livetv.sx/enx/eventinfo/332113457__/",
    "event_id": "332113457",
    "date_time": "8 January at 16:00",
    "competition": "Cyprus. Cup",
    "parsed_datetime": "2026-01-08T16:00:00",
    "logo_alt": "Cyprus. Cup",
    "is_live": false,
    "team_logos": [
      {
        "team_name": "Olympiakos Nicosia",
        "logo_url": "https://cdn.livetv872.me/img/teams/fullsize/ods/6058.gif"
      },
      {
        "team_name": "Omonia Aradippou",
        "logo_url": "https://cdn.livetv872.me/img/teams/fullsize/ods/1230.gif"
      }
    ],
    "streams": []
  },
  {
    "matchup": "Al-Ahli Manama – Al-Budaiya",
    "event_url": "https://livetv.sx/enx/eventinfo/328965850__/",
    "event_id": "328965850",
    "date_time": "8 January at 17:00",
    "competition": "Bahrain. Premier League",
    "parsed_datetime": "2026-01-08T17:00:00",
    "logo_alt": "Bahrain. Premier League",
    "is_live": false,
    "team_logos": [
      {
        "team_name": "Al-Ahli Manama",
        "logo_url": "https://cdn.livetv872.me/img/teams/fullsize/ods/1748.gif"
      },
      {
        "team_name": "Al-Budaiya",
        "logo_url": "https://cdn.livetv872.me/img/teams/fullsize/ods/6747.gif"
      }
    ],
    "streams": []
  },
  {
    "matchup": "Meia Noite U20 – Coritiba U20",
    "event_url": "https://livetv.sx/enx/eventinfo/332235428_meia_noite_u20_coritiba_u20/",
    "event_id": "332235428",
    "date_time": "8 January at 19:15",
    "competition": "Brazil. Sao Paulo Youth Cup",
    "parsed_datetime": "2026-01-08T19:15:00",
    "logo_alt": "Brazil. Sao Paulo Youth Cup",
    "is_live": false,
    "team_logos": [],
    "streams": []
  },
  {
    "matchup": "Qatar SC – Al-Sadd",
    "event_url": "https://livetv.sx/enx/eventinfo/328969701__/",
    "event_id": "328969701",
    "date_time": "8 January at 17:30",
    "competition": "Qatar. Stars League",
    "parsed_datetime": "2026-01-08T17:30:00",
    "logo_alt": "Qatar. Stars League",
    "is_live": false,
    "team_logos": [
      {
        "team_name": "Qatar SC",
        "logo_url": "https://cdn.livetv872.me/img/teams/fullsize/ods/35161.gif"
      },
      {
        "team_name": "Al-Sadd",
        "logo_url": "https://cdn.livetv872.me/img/teams/fullsize/ods/19984.gif"
      }
    ],
    "streams": []
  },
  {
    "matchup": "Al-Najma – Al-Ettifaq",
    "event_url": "https://livetv.sx/enx/eventinfo/328977673__/",
    "event_id": "328977673",
    "date_time": "8 January at 18:30",
    "competition": "Saudi Arabia. Pro League",
    "parsed_datetime": "2026-01-08T18:30:00",
    "logo_alt": "Saudi Arabia. Pro League",
    "is_live": false,
    "team_logos": [
      {
        "team_name": "Al-Najma",
        "logo_url": "https://cdn.livetv872.me/img/teams/fullsize/ods/28981.gif"
      },
      {
        "team_name": "Al-Ettifaq",
        "logo_url": "https://cdn.livetv872.me/img/teams/fullsize/ods/1530.gif"
      }
    ],
    "streams": []
  },
  {
    "matchup": "Al-Merreikh – Police",
    "event_url": "https://livetv.sx/enx/eventinfo/332185084__/",
    "event_id": "332185084",
    "date_time": "8 January at 17:30",
    "competition": "Rwanda. Premier League",
    "parsed_datetime": "2026-01-08T17:30:00",
    "logo_alt": "Rwanda. Premier League",
    "is_live": false,
    "team_logos": [
      {
        "team_name": "Al-Merreikh",
        "logo_url": "https://cdn.livetv872.me/img/teams/fullsize/ods/12142.gif"
      },
      {
        "team_name": "Police",
        "logo_url": "https://cdn.livetv872.me/img/teams/fullsize/ods/36542.gif"
      }
    ],
    "streams": []
  },
  {
    "matchup": "Al Nassr – Al Quadisiya",
    "event_url": "https://livetv.sx/enx/eventinfo/328977674__/",
    "event_id": "328977674",
    "date_time": "8 January at 18:30",
    "competition": "Saudi Arabia. Pro League",
    "parsed_datetime": "2026-01-08T18:30:00",
    "logo_alt": "Saudi Arabia. Pro League",
    "is_live": false,
    "team_logos": [
      {
        "team_name": "Al Nassr",
        "logo_url": "https://cdn.livetv872.me/img/teams/fullsize/ods/35362.gif"
      },
      {
        "team_name": "Al Quadisiya",
        "logo_url": "https://cdn.livetv872.me/img/teams/fullsize/ods/30593.gif"
      }
    ],
    "streams": []
  },
  {
    "matchup": "Atletico Madrid – Real Madrid RM",
    "event_url": "https://livetv.sx/enx/eventinfo/328986655__/",
    "event_id": "328986655",
    "date_time": "8 January at 20:00",
    "competition": "Spain. Super Cup",
    "parsed_datetime": "2026-01-08T20:00:00",
    "logo_alt": "Spain. Super Cup",
    "is_live": false,
    "team_logos": [
      {
        "team_name": "Atletico Madrid",
        "logo_url": "https://cdn.livetv872.me/img/teams/fullsize/ods/35887.gif"
      },
      {
        "team_name": "Real Madrid RM",
        "logo_url": "https://cdn.livetv872.me/img/teams/fullsize/ods/33.gif"
      }
    ],
    "streams": []
  },
  {
    "matchup": "Brasiliense U-20 –  Fluminense PI U-20",
    "event_url": "https://livetv.sx/enx/eventinfo/331991469__/",
    "event_id": "331991469",
    "date_time": "8 January at 20:30",
    "competition": "Brazil. Sao Paulo Youth Cup",
    "parsed_datetime": "2026-01-08T20:30:00",
    "logo_alt": "Brazil. Sao Paulo Youth Cup",
    "is_live": false,
    "team_logos": [
      {
        "team_name": "Brasiliense U-20",
        "logo_url": "https://cdn.livetv872.me/img/teams/fullsize/ods/34796.gif"
      },
      {
        "team_name": "Fluminense PI U-20",
        "logo_url": "https://cdn.livetv872.me/img/teams/fullsize/ods/12970.gif"
      }
    ],
    "streams": []
  },
  {
    "matchup": "Cremonese – Cagliari",
    "event_url": "https://livetv.sx/enx/eventinfo/328976400__/",
    "event_id": "328976400",
    "date_time": "8 January at 18:30",
    "competition": "Italy. Serie A",
    "parsed_datetime": "2026-01-08T18:30:00",
    "logo_alt": "Italy. Serie A",
    "is_live": false,
    "team_logos": [
      {
        "team_name": "Cremonese",
        "logo_url": "https://cdn.livetv872.me/img/teams/fullsize/ods/3913.gif"
      },
      {
        "team_name": "Cagliari",
        "logo_url": "https://cdn.livetv872.me/img/teams/fullsize/ods/62.gif"
      }
    ],
    "streams": []
  },
  {
    "matchup": "PSG – Marseille",
    "event_url": "https://livetv.sx/enx/eventinfo/328981389__/",
    "event_id": "328981389",
    "date_time": "8 January at 19:00",
    "competition": "France. Supercup",
    "parsed_datetime": "2026-01-08T19:00:00",
    "logo_alt": "France. Supercup",
    "is_live": false,
    "team_logos": [
      {
        "team_name": "PSG",
        "logo_url": "https://cdn.livetv872.me/img/teams/fullsize/ods/34520.gif"
      },
      {
        "team_name": "Marseille",
        "logo_url": "https://cdn.livetv872.me/img/teams/fullsize/ods/120.gif"
      }
    ],
    "streams": []
  },
  {
    "matchup": "Brasiliense U-20 –  Fluminense U-20",
    "event_url": "https://livetv.sx/enx/eventinfo/331986009__/",
    "event_id": "331986009",
    "date_time": "8 January at 20:30",
    "competition": "Brazil. Sao Paulo Youth Cup",
    "parsed_datetime": "2026-01-08T20:30:00",
    "logo_alt": "Brazil. Sao Paulo Youth Cup",
    "is_live": false,
    "team_logos": [
      {
        "team_name": "Brasiliense U-20",
        "logo_url": "https://cdn.livetv872.me/img/teams/fullsize/ods/34796.gif"
      },
      {
        "team_name": "Fluminense U-20",
        "logo_url": "https://cdn.livetv872.me/img/teams/fullsize/ods/9071.gif"
      }
    ],
    "streams": []
  },
  {
    "matchup": "Milan – Genoa",
    "event_url": "https://livetv.sx/enx/eventinfo/328993655__/",
    "event_id": "328993655",
    "date_time": "8 January at 20:45",
    "competition": "Italy. Serie A",
    "parsed_datetime": "2026-01-08T20:45:00",
    "logo_alt": "Italy. Serie A",
    "is_live": false,
    "team_logos": [
      {
        "team_name": "Milan",
        "logo_url": "https://cdn.livetv872.me/img/teams/fullsize/ods/56.gif"
      },
      {
        "team_name": "Genoa",
        "logo_url": "https://cdn.livetv872.me/img/teams/fullsize/ods/71.gif"
      }
    ],
    "streams": []
  },
  {
    "matchup": "India – Mexico",
    "event_url": "https://livetv.sx/enx/eventinfo/331417749_india_mexico/",
    "event_id": "331417749",
    "date_time": "8 January at 22:00",
    "competition": "Friendly Tournament. National Teams",
    "parsed_datetime": "2026-01-08T22:00:00",
    "logo_alt": "Friendly Tournament. National Teams",
    "is_live": false,
    "team_logos": [
      {
        "team_name": "India",
        "logo_url": "https://cdn.livetv872.me/img/teams/fullsize/130.gif"
      },
      {
        "team_name": "Mexico",
        "logo_url": "https://cdn.livetv872.me/img/teams/fullsize/265.gif"
      }
    ],
    "streams": []
  },
  {
    "matchup": "Monte Roraima U-20 –  Remo U-20",
    "event_url": "https://livetv.sx/enx/eventinfo/331953213__/",
    "event_id": "331953213",
    "date_time": "8 January at 21:15",
    "competition": "Brazil. Sao Paulo Youth Cup",
    "parsed_datetime": "2026-01-08T21:15:00",
    "logo_alt": "Brazil. Sao Paulo Youth Cup",
    "is_live": false,
    "team_logos": [
      {
        "team_name": "Monte Roraima U-20",
        "logo_url": "https://cdn.livetv872.me/img/teams/fullsize/ods/32240.gif"
      },
      {
        "team_name": "Remo U-20",
        "logo_url": "https://cdn.livetv872.me/img/teams/fullsize/ods/23482.gif"
      }
    ],
    "streams": []
  },
  {
    "matchup": "Lusitania – Leixoes",
    "event_url": "https://livetv.sx/enx/eventinfo/328998230__/",
    "event_id": "328998230",
    "date_time": "8 January at 21:15",
    "competition": "Portugal. Segunda Liga",
    "parsed_datetime": "2026-01-08T21:15:00",
    "logo_alt": "Portugal. Segunda Liga",
    "is_live": false,
    "team_logos": [
      {
        "team_name": "Lusitania",
        "logo_url": "https://cdn.livetv872.me/img/teams/fullsize/ods/11905.gif"
      },
      {
        "team_name": "Leixoes",
        "logo_url": "https://cdn.livetv872.me/img/teams/fullsize/ods/4380.gif"
      }
    ],
    "streams": []
  },
  {
    "matchup": "Arsenal – Liverpool",
    "event_url": "https://livetv.sx/enx/eventinfo/328993067__/",
    "event_id": "328993067",
    "date_time": "8 January at 21:00",
    "competition": "England. Premier League",
    "parsed_datetime": "2026-01-08T21:00:00",
    "logo_alt": "England. Premier League",
    "is_live": false,
    "team_logos": [
      {
        "team_name": "Arsenal",
        "logo_url": "https://cdn.livetv872.me/img/teams/fullsize/ods/142.gif"
      },
      {
        "team_name": "Liverpool",
        "logo_url": "https://cdn.livetv872.me/img/teams/fullsize/ods/30918.gif"
      }
    ],
    "streams": []
  },
  {
    "matchup": "Linense U-20 –  Forte U-20",
    "event_url": "https://livetv.sx/enx/eventinfo/331953214__/",
    "event_id": "331953214",
    "date_time": "8 January at 22:15",
    "competition": "Brazil. Sao Paulo Youth Cup",
    "parsed_datetime": "2026-01-08T22:15:00",
    "logo_alt": "Brazil. Sao Paulo Youth Cup",
    "is_live": false,
    "team_logos": [
      {
        "team_name": "Linense U-20",
        "logo_url": "https://cdn.livetv872.me/img/teams/fullsize/ods/9796.gif"
      },
      {
        "team_name": "Forte U-20",
        "logo_url": "https://cdn.livetv872.me/img/teams/fullsize/ods/36895.gif"
      }
    ],
    "streams": []
  },
  {
    "matchup": "Qatar – Brazil",
    "event_url": "https://livetv.sx/enx/eventinfo/331417750_qatar_brazil/",
    "event_id": "331417750",
    "date_time": "8 January at 23:00",
    "competition": "Friendly Tournament. National Teams",
    "parsed_datetime": "2026-01-08T23:00:00",
    "logo_alt": "Friendly Tournament. National Teams",
    "is_live": false,
    "team_logos": [
      {
        "team_name": "Qatar",
        "logo_url": "https://cdn.livetv872.me/img/teams/fullsize/102.gif"
      },
      {
        "team_name": "Brazil",
        "logo_url": "https://cdn.livetv872.me/img/teams/fullsize/857.gif"
      }
    ],
    "streams": []
  },
  {
    "matchup": "Sfera SP U-20 –  Agua Santa U-20",
    "event_url": "https://livetv.sx/enx/eventinfo/331975056__/",
    "event_id": "331975056",
    "date_time": "8 January at 22:45",
    "competition": "Brazil. Sao Paulo Youth Cup",
    "parsed_datetime": "2026-01-08T22:45:00",
    "logo_alt": "Brazil. Sao Paulo Youth Cup",
    "is_live": false,
    "team_logos": [
      {
        "team_name": "Sfera SP U-20",
        "logo_url": "https://cdn.livetv872.me/img/teams/fullsize/ods/28625.gif"
      },
      {
        "team_name": "Agua Santa U-20",
        "logo_url": "https://cdn.livetv872.me/img/teams/fullsize/ods/9416.gif"
      }
    ],
    "streams": []
  },
  {
    "matchup": "Cascavel – Azuriz",
    "event_url": "https://livetv.sx/enx/eventinfo/329006828__/",
    "event_id": "329006828",
    "date_time": "8 January at 23:00",
    "competition": "Brazil. Campeonato Paranaense",
    "parsed_datetime": "2026-01-08T23:00:00",
    "logo_alt": "Brazil. Campeonato Paranaense",
    "is_live": false,
    "team_logos": [
      {
        "team_name": "Cascavel",
        "logo_url": "https://cdn.livetv872.me/img/teams/fullsize/ods/29904.gif"
      },
      {
        "team_name": "Azuriz",
        "logo_url": "https://cdn.livetv872.me/img/teams/fullsize/ods/29821.gif"
      }
    ],
    "streams": []
  },
  {
    "matchup": "Falcon U-20 –  Galvez U-20",
    "event_url": "https://livetv.sx/enx/eventinfo/331986013__/",
    "event_id": "331986013",
    "date_time": "8 January at 23:15",
    "competition": "Brazil. Sao Paulo Youth Cup",
    "parsed_datetime": "2026-01-08T23:15:00",
    "logo_alt": "Brazil. Sao Paulo Youth Cup",
    "is_live": false,
    "team_logos": [
      {
        "team_name": "Falcon U-20",
        "logo_url": "https://cdn.livetv872.me/img/teams/fullsize/ods/25204.gif"
      },
      {
        "team_name": "Galvez U-20",
        "logo_url": "https://cdn.livetv872.me/img/teams/fullsize/ods/13001.gif"
      }
    ],
    "streams": []
  },
  {
    "matchup": "Palmeiras U-20 –  Batalhao U-20",
    "event_url": "https://livetv.sx/enx/eventinfo/331996892__/",
    "event_id": "331996892",
    "date_time": "8 January at 23:30",
    "competition": "Brazil. Sao Paulo Youth Cup",
    "parsed_datetime": "2026-01-08T23:30:00",
    "logo_alt": "Brazil. Sao Paulo Youth Cup",
    "is_live": false,
    "team_logos": [
      {
        "team_name": "Palmeiras U-20",
        "logo_url": "https://cdn.livetv872.me/img/teams/fullsize/ods/9008.gif"
      },
      {
        "team_name": "Batalhao U-20",
        "logo_url": "https://cdn.livetv872.me/img/teams/fullsize/ods/0.gif"
      }
    ],
    "streams": []
  }
]