[
  {
    "matchup": "Sporting – Rio Ave",
    "event_url": "https://livetv.sx/enx/eventinfo/326716564__/",
    "event_id": "326716564",
    "date_time": "28 December at 21:30",
    "competition": "Portugal. Primeira Liga",
    "parsed_datetime": "2025-12-28T21:30:00",
    "logo_alt": "Portugal. Primeira Liga",
    "is_live": false,
    "team_logos": [
      {
        "team_name": "Sporting",
        "logo_url": "https://cdn.livetv872.me/img/teams/fullsize/ods/340.gif"
      },
      {
        "team_name": "Rio Ave",
        "logo_url": "https://cdn.livetv872.me/img/teams/fullsize/ods/1120.gif"
      }
    ],
    "streams": []
  },
  {
    "matchup": "Sporting – Rio Ave",
    "event_url": "https://livetv.sx/enx/eventinfo/326716564__/",
    "event_id": "326716564",
    "date_time": "28 December at 21:30",
    "competition": "Portugal. Primeira Liga",
    "parsed_datetime": "2025-12-28T21:30:00",
    "logo_alt": "Portugal. Primeira Liga",
    "is_live": false,
    "team_logos": [
      {
        "team_name": "Sporting",
        "logo_url": "https://cdn.livetv872.me/img/teams/fullsize/ods/340.gif"
      },
      {
        "team_name": "Rio Ave",
        "logo_url": "https://cdn.livetv872.me/img/teams/fullsize/ods/1120.gif"
      }
    ],
    "streams": []
  }
]